LICENSE
README.md
pyproject.toml
setup.cfg
docs/en/abbreviation.md
docs/en/api.rst
docs/en/conf.py
docs/en/customization.md
docs/en/index.rst
docs/en/installation.md
mim/__init__.py
mim/__main__.py
mim/cli.py
mim/version.py
mim/_internal/export/README.md
mim/_internal/export/__init__.py
mim/_internal/export/common.py
mim/_internal/export/flatten_func.py
mim/_internal/export/pack_cfg.py
mim/_internal/export/utils.py
mim/_internal/export/patch_utils/README.md
mim/_internal/export/patch_utils/README_zh-CN.md
mim/_internal/export/patch_utils/__init__.py
mim/_internal/export/patch_utils/patch_model.py
mim/_internal/export/patch_utils/patch_task.py
mim/click/__init__.py
mim/click/autocompletion.py
mim/click/compat.py
mim/click/customcommand.py
mim/click/option.py
mim/click/utils.py
mim/commands/__init__.py
mim/commands/download.py
mim/commands/export.py
mim/commands/gridsearch.py
mim/commands/install.py
mim/commands/list.py
mim/commands/run.py
mim/commands/search.py
mim/commands/test.py
mim/commands/train.py
mim/commands/uninstall.py
mim/utils/__init__.py
mim/utils/default.py
mim/utils/progress_bars.py
mim/utils/utils.py
onedl_mim.egg-info/PKG-INFO
onedl_mim.egg-info/SOURCES.txt
onedl_mim.egg-info/dependency_links.txt
onedl_mim.egg-info/entry_points.txt
onedl_mim.egg-info/requires.txt
onedl_mim.egg-info/top_level.txt
tests/README.md
tests/test_download.py
tests/test_gridsearch.py
tests/test_install.py
tests/test_list.py
tests/test_run.py
tests/test_search.py
tests/test_test.py
tests/test_train.py
tests/test_uninstall.py
tests/test_utils.py
tests/test_version.py
tests/data/lenet5_mnist_2.0.py