Metadata-Version: 2.4
Name: onedl-mim
Version: 0.4.0rc2
Summary: MIM Installs OneDL lab packages
Author-email: OneDL-Mim Contributors <oss-team@vbti.nl>
License: Apache-2.0
Project-URL: Homepage, https://github.com/vbti-development/onedl-mim
Project-URL: Repository, https://github.com/vbti-development/onedl-mim
Project-URL: Documentation, https://onedl-openmim.readthedocs.io
Project-URL: Bug Tracker, https://github.com/vbti-development/onedl-mim/issues
Keywords: computer vision,deep learning,pytorch,onedl
Classifier: Development Status :: 4 - Beta
Classifier: Operating System :: OS Independent
Classifier: Programming Language :: Python :: 3
Classifier: Programming Language :: Python :: 3.10
Classifier: Programming Language :: Python :: 3.11
Classifier: Topic :: Scientific/Engineering :: Artificial Intelligence
Classifier: Topic :: Software Development :: Libraries :: Python Modules
Requires-Python: >=3.10
License-File: LICENSE
Requires-Dist: Click
Requires-Dist: colorama
Requires-Dist: model-index
Requires-Dist: opendatalab
Requires-Dist: pandas
Requires-Dist: pip>=19.3
Requires-Dist: requests
Requires-Dist: rich
Requires-Dist: tabulate
Requires-Dist: numpy<2
Provides-Extra: torch
Requires-Dist: torch; extra == "torch"
Requires-Dist: torchvision; extra == "torch"
Dynamic: license-file
